[{"InstanceId":"2c02bdc236774b6ab025270bff1e6446","Name":"Jab 1","OwnerId":12,"Owner":"DuckHunt","HitboxActive":"4-6","FirstActionableFrame":"26","BaseDamage":"2.5","Angle":"68/82","BaseKnockBackSetKnockback":"W: 30/25","LandingLag":null,"AutoCancel":null,"KnockbackGrowth":"100","MoveType":"ground","IsWeightDependent":false,"Game":"Smash4","Related":{"Smash4":{"Character":"http://api.kuroganehammer.com/api/characters/name/DuckHunt?game=smash4","Self":"http://api.kuroganehammer.com/api/moves/2c02bdc236774b6ab025270bff1e6446?game=smash4"},"Ultimate":{"Character":"http://api.kuroganehammer.com/api/characters/name/DuckHunt?game=ultimate"}},"Links":[{"Rel":"self","Href":"http://api.kuroganehammer.com/api/moves/2c02bdc236774b6ab025270bff1e6446?game=smash4"},{"Rel":"character","Href":"http://api.kuroganehammer.com/api/characters/name/DuckHunt?game=smash4"}]},{"InstanceId":"82d9e234be0644a991a1c8c4d3f2b63d","Name":"Jab 2","OwnerId":12,"Owner":"DuckHunt","HitboxActive":"5-7","FirstActionableFrame":"28","BaseDamage":"2.5","Angle":"60/70","BaseKnockBackSetKnockback":"W: 35/25","LandingLag":null,"AutoCancel":null,"KnockbackGrowth":"100","MoveType":"ground","IsWeightDependent":false,"Game":"Smash4","Related":{"Smash4":{"Character":"http://api.kuroganehammer.com/api/characters/name/DuckHunt?game=smash4","Self":"http://api.kuroganehammer.com/api/moves/82d9e234be0644a991a1c8c4d3f2b63d?game=smash4"},"Ultimate":{"Character":"http://api.kuroganehammer.com/api/characters/name/DuckHunt?game=ultimate"}},"Links":[{"Rel":"self","Href":"http://api.kuroganehammer.com/api/moves/82d9e234be0644a991a1c8c4d3f2b63d?game=smash4"},{"Rel":"character","Href":"http://api.kuroganehammer.com/api/characters/name/DuckHunt?game=smash4"}]},{"InstanceId":"754f7c01f7054539b4c51571922a7b28","Name":"Jab 3","OwnerId":12,"Owner":"DuckHunt","HitboxActive":"6-9","FirstActionableFrame":"34","BaseDamage":"5","Angle":"60","BaseKnockBackSetKnockback":"50","LandingLag":null,"AutoCancel":null,"KnockbackGrowth":"130","MoveType":"ground","IsWeightDependent":false,"Game":"Smash4","Related":{"Smash4":{"Character":"http://api.kuroganehammer.com/api/characters/name/DuckHunt?game=smash4","Self":"http://api.kuroganehammer.com/api/moves/754f7c01f7054539b4c51571922a7b28?game=smash4"},"Ultimate":{"Character":"http://api.kuroganehammer.com/api/characters/name/DuckHunt?game=ultimate"}},"Links":[{"Rel":"self","Href":"http://api.kuroganehammer.com/api/moves/754f7c01f7054539b4c51571922a7b28?game=smash4"},{"Rel":"character","Href":"http://api.kuroganehammer.com/api/characters/name/DuckHunt?game=smash4"}]},{"InstanceId":"d4852188c9e54691bc82a486e4c741ee","Name":"Rapid Jab","OwnerId":12,"Owner":"DuckHunt","HitboxActive":"-","FirstActionableFrame":"-","BaseDamage":"1","Angle":"80","BaseKnockBackSetKnockback":"W: 16","LandingLag":null,"AutoCancel":null,"KnockbackGrowth":"100","MoveType":"ground","IsWeightDependent":false,"Game":"Smash4","Related":{"Smash4":{"Character":"http://api.kuroganehammer.com/api/characters/name/DuckHunt?game=smash4","Self":"http://api.kuroganehammer.com/api/moves/d4852188c9e54691bc82a486e4c741ee?game=smash4"},"Ultimate":{"Character":"http://api.kuroganehammer.com/api/characters/name/DuckHunt?game=ultimate"}},"Links":[{"Rel":"self","Href":"http://api.kuroganehammer.com/api/moves/d4852188c9e54691bc82a486e4c741ee?game=smash4"},{"Rel":"character","Href":"http://api.kuroganehammer.com/api/characters/name/DuckHunt?game=smash4"}]},{"InstanceId":"52a48445d7a2425a8f339c782ca73fcc","Name":"Rapid Jab Finisher","OwnerId":12,"Owner":"DuckHunt","HitboxActive":"6","FirstActionableFrame":"40","BaseDamage":"3","Angle":"74","BaseKnockBackSetKnockback":"70","LandingLag":null,"AutoCancel":null,"KnockbackGrowth":"140","MoveType":"ground","IsWeightDependent":false,"Game":"Smash4","Related":{"Smash4":{"Character":"http://api.kuroganehammer.com/api/characters/name/DuckHunt?game=smash4","Self":"http://api.kuroganehammer.com/api/moves/52a48445d7a2425a8f339c782ca73fcc?game=smash4"},"Ultimate":{"Character":"http://api.kuroganehammer.com/api/characters/name/DuckHunt?game=ultimate"}},"Links":[{"Rel":"self","Href":"http://api.kuroganehammer.com/api/moves/52a48445d7a2425a8f339c782ca73fcc?game=smash4"},{"Rel":"character","Href":"http://api.kuroganehammer.com/api/characters/name/DuckHunt?game=smash4"}]},{"InstanceId":"61223a3909e14dcf8d74596776579646","Name":"Dash Attack","OwnerId":12,"Owner":"DuckHunt","HitboxActive":"10-13","FirstActionableFrame":"44","BaseDamage":"10","Angle":"60","BaseKnockBackSetKnockback":"100","LandingLag":null,"AutoCancel":null,"KnockbackGrowth":"40","MoveType":"ground","IsWeightDependent":false,"Game":"Smash4","Related":{"Smash4":{"Character":"http://api.kuroganehammer.com/api/characters/name/DuckHunt?game=smash4","Self":"http://api.kuroganehammer.com/api/moves/61223a3909e14dcf8d74596776579646?game=smash4"},"Ultimate":{"Character":"http://api.kuroganehammer.com/api/characters/name/DuckHunt?game=ultimate"}},"Links":[{"Rel":"self","Href":"http://api.kuroganehammer.com/api/moves/61223a3909e14dcf8d74596776579646?game=smash4"},{"Rel":"character","Href":"http://api.kuroganehammer.com/api/characters/name/DuckHunt?game=smash4"}]},{"InstanceId":"4c6f28657d9e4b2186df97990d1b6f88","Name":"Dash Attack (Late)","OwnerId":12,"Owner":"DuckHunt","HitboxActive":"14-19","FirstActionableFrame":"-","BaseDamage":"7","Angle":"110","BaseKnockBackSetKnockback":"100","LandingLag":null,"AutoCancel":null,"KnockbackGrowth":"40","MoveType":"ground","IsWeightDependent":false,"Game":"Smash4","Related":{"Smash4":{"Character":"http://api.kuroganehammer.com/api/characters/name/DuckHunt?game=smash4","Self":"http://api.kuroganehammer.com/api/moves/4c6f28657d9e4b2186df97990d1b6f88?game=smash4"},"Ultimate":{"Character":"http://api.kuroganehammer.com/api/characters/name/DuckHunt?game=ultimate"}},"Links":[{"Rel":"self","Href":"http://api.kuroganehammer.com/api/moves/4c6f28657d9e4b2186df97990d1b6f88?game=smash4"},{"Rel":"character","Href":"http://api.kuroganehammer.com/api/characters/name/DuckHunt?game=smash4"}]},{"InstanceId":"10bbc1fd2db147b88894336bc39b9f39","Name":"Ftilt (All Angles)","OwnerId":12,"Owner":"DuckHunt","HitboxActive":"8-11","FirstActionableFrame":"32","BaseDamage":"8","Angle":"361","BaseKnockBackSetKnockback":"15","LandingLag":null,"AutoCancel":null,"KnockbackGrowth":"100","MoveType":"ground","IsWeightDependent":false,"Game":"Smash4","Related":{"Smash4":{"Character":"http://api.kuroganehammer.com/api/characters/name/DuckHunt?game=smash4","Self":"http://api.kuroganehammer.com/api/moves/10bbc1fd2db147b88894336bc39b9f39?game=smash4"},"Ultimate":{"Character":"http://api.kuroganehammer.com/api/characters/name/DuckHunt?game=ultimate"}},"Links":[{"Rel":"self","Href":"http://api.kuroganehammer.com/api/moves/10bbc1fd2db147b88894336bc39b9f39?game=smash4"},{"Rel":"character","Href":"http://api.kuroganehammer.com/api/characters/name/DuckHunt?game=smash4"}]},{"InstanceId":"bdc2166adad049b29a619b5482273420","Name":"Utilt","OwnerId":12,"Owner":"DuckHunt","HitboxActive":"8-12","FirstActionableFrame":"34","BaseDamage":"7","Angle":"96","BaseKnockBackSetKnockback":"35","LandingLag":null,"AutoCancel":null,"KnockbackGrowth":"130","MoveType":"ground","IsWeightDependent":false,"Game":"Smash4","Related":{"Smash4":{"Character":"http://api.kuroganehammer.com/api/characters/name/DuckHunt?game=smash4","Self":"http://api.kuroganehammer.com/api/moves/bdc2166adad049b29a619b5482273420?game=smash4"},"Ultimate":{"Character":"http://api.kuroganehammer.com/api/characters/name/DuckHunt?game=ultimate"}},"Links":[{"Rel":"self","Href":"http://api.kuroganehammer.com/api/moves/bdc2166adad049b29a619b5482273420?game=smash4"},{"Rel":"character","Href":"http://api.kuroganehammer.com/api/characters/name/DuckHunt?game=smash4"}]},{"InstanceId":"4209bcc01dbe4f4dac3bd687a6cc77be","Name":"Dtilt","OwnerId":12,"Owner":"DuckHunt","HitboxActive":"6-7","FirstActionableFrame":"35","BaseDamage":"8","Angle":"30","BaseKnockBackSetKnockback":"50","LandingLag":null,"AutoCancel":null,"KnockbackGrowth":"60","MoveType":"ground","IsWeightDependent":false,"Game":"Smash4","Related":{"Smash4":{"Character":"http://api.kuroganehammer.com/api/characters/name/DuckHunt?game=smash4","Self":"http://api.kuroganehammer.com/api/moves/4209bcc01dbe4f4dac3bd687a6cc77be?game=smash4"},"Ultimate":{"Character":"http://api.kuroganehammer.com/api/characters/name/DuckHunt?game=ultimate"}},"Links":[{"Rel":"self","Href":"http://api.kuroganehammer.com/api/moves/4209bcc01dbe4f4dac3bd687a6cc77be?game=smash4"},{"Rel":"character","Href":"http://api.kuroganehammer.com/api/characters/name/DuckHunt?game=smash4"}]},{"InstanceId":"d78a4cd71da74daea77ee33d957be3b1","Name":"Fsmash (Hits 1-2)","OwnerId":12,"Owner":"DuckHunt","HitboxActive":"17-18, 23-24","FirstActionableFrame":"67","BaseDamage":"4","Angle":"5","BaseKnockBackSetKnockback":"W: 60","LandingLag":null,"AutoCancel":null,"KnockbackGrowth":"100","MoveType":"ground","IsWeightDependent":false,"Game":"Smash4","Related":{"Smash4":{"Character":"http://api.kuroganehammer.com/api/characters/name/DuckHunt?game=smash4","Self":"http://api.kuroganehammer.com/api/moves/d78a4cd71da74daea77ee33d957be3b1?game=smash4"},"Ultimate":{"Character":"http://api.kuroganehammer.com/api/characters/name/DuckHunt?game=ultimate"}},"Links":[{"Rel":"self","Href":"http://api.kuroganehammer.com/api/moves/d78a4cd71da74daea77ee33d957be3b1?game=smash4"},{"Rel":"character","Href":"http://api.kuroganehammer.com/api/characters/name/DuckHunt?game=smash4"}]},{"InstanceId":"534a88cd18474102a70fdb2a4a0742de","Name":"Fsmash (Hit 3)","OwnerId":12,"Owner":"DuckHunt","HitboxActive":"29-30","FirstActionableFrame":"-","BaseDamage":"9","Angle":"361","BaseKnockBackSetKnockback":"50","LandingLag":null,"AutoCancel":null,"KnockbackGrowth":"125","MoveType":"ground","IsWeightDependent":false,"Game":"Smash4","Related":{"Smash4":{"Character":"http://api.kuroganehammer.com/api/characters/name/DuckHunt?game=smash4","Self":"http://api.kuroganehammer.com/api/moves/534a88cd18474102a70fdb2a4a0742de?game=smash4"},"Ultimate":{"Character":"http://api.kuroganehammer.com/api/characters/name/DuckHunt?game=ultimate"}},"Links":[{"Rel":"self","Href":"http://api.kuroganehammer.com/api/moves/534a88cd18474102a70fdb2a4a0742de?game=smash4"},{"Rel":"character","Href":"http://api.kuroganehammer.com/api/characters/name/DuckHunt?game=smash4"}]},{"InstanceId":"76b73e28afce443ab63ba0130527a56a","Name":"Usmash (Hit 1)","OwnerId":12,"Owner":"DuckHunt","HitboxActive":"12-13","FirstActionableFrame":"58","BaseDamage":"2","Angle":"140/150","BaseKnockBackSetKnockback":"W: 72/60","LandingLag":null,"AutoCancel":null,"KnockbackGrowth":"110/100","MoveType":"ground","IsWeightDependent":false,"Game":"Smash4","Related":{"Smash4":{"Character":"http://api.kuroganehammer.com/api/characters/name/DuckHunt?game=smash4","Self":"http://api.kuroganehammer.com/api/moves/76b73e28afce443ab63ba0130527a56a?game=smash4"},"Ultimate":{"Character":"http://api.kuroganehammer.com/api/characters/name/DuckHunt?game=ultimate"}},"Links":[{"Rel":"self","Href":"http://api.kuroganehammer.com/api/moves/76b73e28afce443ab63ba0130527a56a?game=smash4"},{"Rel":"character","Href":"http://api.kuroganehammer.com/api/characters/name/DuckHunt?game=smash4"}]},{"InstanceId":"00c505a4ca2f442b8797a2c77fb42f26","Name":"Usmash (Hit 2)","OwnerId":12,"Owner":"DuckHunt","HitboxActive":"20-21","FirstActionableFrame":"-","BaseDamage":"2.4","Angle":"115","BaseKnockBackSetKnockback":"W: 72","LandingLag":null,"AutoCancel":null,"KnockbackGrowth":"100","MoveType":"ground","IsWeightDependent":false,"Game":"Smash4","Related":{"Smash4":{"Character":"http://api.kuroganehammer.com/api/characters/name/DuckHunt?game=smash4","Self":"http://api.kuroganehammer.com/api/moves/00c505a4ca2f442b8797a2c77fb42f26?game=smash4"},"Ultimate":{"Character":"http://api.kuroganehammer.com/api/characters/name/DuckHunt?game=ultimate"}},"Links":[{"Rel":"self","Href":"http://api.kuroganehammer.com/api/moves/00c505a4ca2f442b8797a2c77fb42f26?game=smash4"},{"Rel":"character","Href":"http://api.kuroganehammer.com/api/characters/name/DuckHunt?game=smash4"}]},{"InstanceId":"83641bebfb3341f6a94c5e17fe039dcc","Name":"Usmash (Hit 3)","OwnerId":12,"Owner":"DuckHunt","HitboxActive":"28-29","FirstActionableFrame":"-","BaseDamage":"10","Angle":"85","BaseKnockBackSetKnockback":"40","LandingLag":null,"AutoCancel":null,"KnockbackGrowth":"112","MoveType":"ground","IsWeightDependent":false,"Game":"Smash4","Related":{"Smash4":{"Character":"http://api.kuroganehammer.com/api/characters/name/DuckHunt?game=smash4","Self":"http://api.kuroganehammer.com/api/moves/83641bebfb3341f6a94c5e17fe039dcc?game=smash4"},"Ultimate":{"Character":"http://api.kuroganehammer.com/api/characters/name/DuckHunt?game=ultimate"}},"Links":[{"Rel":"self","Href":"http://api.kuroganehammer.com/api/moves/83641bebfb3341f6a94c5e17fe039dcc?game=smash4"},{"Rel":"character","Href":"http://api.kuroganehammer.com/api/characters/name/DuckHunt?game=smash4"}]},{"InstanceId":"ae1f85ee94df4907845015edbef94b5e","Name":"Dsmash (Hit 1)","OwnerId":12,"Owner":"DuckHunt","HitboxActive":"12-13","FirstActionableFrame":"59","BaseDamage":"5","Angle":"165","BaseKnockBackSetKnockback":"W: 115","LandingLag":null,"AutoCancel":null,"KnockbackGrowth":"105","MoveType":"ground","IsWeightDependent":false,"Game":"Smash4","Related":{"Smash4":{"Character":"http://api.kuroganehammer.com/api/characters/name/DuckHunt?game=smash4","Self":"http://api.kuroganehammer.com/api/moves/ae1f85ee94df4907845015edbef94b5e?game=smash4"},"Ultimate":{"Character":"http://api.kuroganehammer.com/api/characters/name/DuckHunt?game=ultimate"}},"Links":[{"Rel":"self","Href":"http://api.kuroganehammer.com/api/moves/ae1f85ee94df4907845015edbef94b5e?game=smash4"},{"Rel":"character","Href":"http://api.kuroganehammer.com/api/characters/name/DuckHunt?game=smash4"}]},{"InstanceId":"4d572ba9231e43d8ba25615f23d47694","Name":"Dsmash (Hit 2)","OwnerId":12,"Owner":"DuckHunt","HitboxActive":"20-21","FirstActionableFrame":"-","BaseDamage":"5","Angle":"165","BaseKnockBackSetKnockback":"W: 115","LandingLag":null,"AutoCancel":null,"KnockbackGrowth":"100","MoveType":"ground","IsWeightDependent":false,"Game":"Smash4","Related":{"Smash4":{"Character":"http://api.kuroganehammer.com/api/characters/name/DuckHunt?game=smash4","Self":"http://api.kuroganehammer.com/api/moves/4d572ba9231e43d8ba25615f23d47694?game=smash4"},"Ultimate":{"Character":"http://api.kuroganehammer.com/api/characters/name/DuckHunt?game=ultimate"}},"Links":[{"Rel":"self","Href":"http://api.kuroganehammer.com/api/moves/4d572ba9231e43d8ba25615f23d47694?game=smash4"},{"Rel":"character","Href":"http://api.kuroganehammer.com/api/characters/name/DuckHunt?game=smash4"}]},{"InstanceId":"00481b64f0ae4dd886ba2ee721b1c1bd","Name":"Dsmash (Hit 3)","OwnerId":12,"Owner":"DuckHunt","HitboxActive":"28-29","FirstActionableFrame":"-","BaseDamage":"6","Angle":"150","BaseKnockBackSetKnockback":"32","LandingLag":null,"AutoCancel":null,"KnockbackGrowth":"155","MoveType":"ground","IsWeightDependent":false,"Game":"Smash4","Related":{"Smash4":{"Character":"http://api.kuroganehammer.com/api/characters/name/DuckHunt?game=smash4","Self":"http://api.kuroganehammer.com/api/moves/00481b64f0ae4dd886ba2ee721b1c1bd?game=smash4"},"Ultimate":{"Character":"http://api.kuroganehammer.com/api/characters/name/DuckHunt?game=ultimate"}},"Links":[{"Rel":"self","Href":"http://api.kuroganehammer.com/api/moves/00481b64f0ae4dd886ba2ee721b1c1bd?game=smash4"},{"Rel":"character","Href":"http://api.kuroganehammer.com/api/characters/name/DuckHunt?game=smash4"}]},{"InstanceId":"75a698e691f74243b390447aa4dc14ea","Name":"Standing Grab","OwnerId":12,"Owner":"DuckHunt","HitboxActive":"8-9","FirstActionableFrame":"29","BaseDamage":"","Angle":"","BaseKnockBackSetKnockback":"","LandingLag":null,"AutoCancel":null,"KnockbackGrowth":"","MoveType":"ground","IsWeightDependent":false,"Game":"Smash4","Related":{"Smash4":{"Character":"http://api.kuroganehammer.com/api/characters/name/DuckHunt?game=smash4","Self":"http://api.kuroganehammer.com/api/moves/75a698e691f74243b390447aa4dc14ea?game=smash4"},"Ultimate":{"Character":"http://api.kuroganehammer.com/api/characters/name/DuckHunt?game=ultimate"}},"Links":[{"Rel":"self","Href":"http://api.kuroganehammer.com/api/moves/75a698e691f74243b390447aa4dc14ea?game=smash4"},{"Rel":"character","Href":"http://api.kuroganehammer.com/api/characters/name/DuckHunt?game=smash4"}]},{"InstanceId":"5dbbfd4543fd4b7087390791dbef1f45","Name":"Dash Grab","OwnerId":12,"Owner":"DuckHunt","HitboxActive":"10-11","FirstActionableFrame":"36","BaseDamage":"","Angle":"","BaseKnockBackSetKnockback":"","LandingLag":null,"AutoCancel":null,"KnockbackGrowth":"","MoveType":"ground","IsWeightDependent":false,"Game":"Smash4","Related":{"Smash4":{"Character":"http://api.kuroganehammer.com/api/characters/name/DuckHunt?game=smash4","Self":"http://api.kuroganehammer.com/api/moves/5dbbfd4543fd4b7087390791dbef1f45?game=smash4"},"Ultimate":{"Character":"http://api.kuroganehammer.com/api/characters/name/DuckHunt?game=ultimate"}},"Links":[{"Rel":"self","Href":"http://api.kuroganehammer.com/api/moves/5dbbfd4543fd4b7087390791dbef1f45?game=smash4"},{"Rel":"character","Href":"http://api.kuroganehammer.com/api/characters/name/DuckHunt?game=smash4"}]},{"InstanceId":"5691e48c9d844e0b8357a618c6a8581f","Name":"Pivot Grab","OwnerId":12,"Owner":"DuckHunt","HitboxActive":"10-11","FirstActionableFrame":"34","BaseDamage":"","Angle":"","BaseKnockBackSetKnockback":"","LandingLag":null,"AutoCancel":null,"KnockbackGrowth":"","MoveType":"ground","IsWeightDependent":false,"Game":"Smash4","Related":{"Smash4":{"Character":"http://api.kuroganehammer.com/api/characters/name/DuckHunt?game=smash4","Self":"http://api.kuroganehammer.com/api/moves/5691e48c9d844e0b8357a618c6a8581f?game=smash4"},"Ultimate":{"Character":"http://api.kuroganehammer.com/api/characters/name/DuckHunt?game=ultimate"}},"Links":[{"Rel":"self","Href":"http://api.kuroganehammer.com/api/moves/5691e48c9d844e0b8357a618c6a8581f?game=smash4"},{"Rel":"character","Href":"http://api.kuroganehammer.com/api/characters/name/DuckHunt?game=smash4"}]},{"InstanceId":"e1da4a69f59e4d6aa653ed47ca7fd90d","Name":"Spotdodge","OwnerId":12,"Owner":"DuckHunt","HitboxActive":"2-16","FirstActionableFrame":"25","BaseDamage":"","Angle":"","BaseKnockBackSetKnockback":"","LandingLag":null,"AutoCancel":null,"KnockbackGrowth":"","MoveType":"ground","IsWeightDependent":false,"Game":"Smash4","Related":{"Smash4":{"Character":"http://api.kuroganehammer.com/api/characters/name/DuckHunt?game=smash4","Self":"http://api.kuroganehammer.com/api/moves/e1da4a69f59e4d6aa653ed47ca7fd90d?game=smash4"},"Ultimate":{"Character":"http://api.kuroganehammer.com/api/characters/name/DuckHunt?game=ultimate"}},"Links":[{"Rel":"self","Href":"http://api.kuroganehammer.com/api/moves/e1da4a69f59e4d6aa653ed47ca7fd90d?game=smash4"},{"Rel":"character","Href":"http://api.kuroganehammer.com/api/characters/name/DuckHunt?game=smash4"}]},{"InstanceId":"9782dd8ccc7d4d3086fa86c4c8786630","Name":"Forward Roll","OwnerId":12,"Owner":"DuckHunt","HitboxActive":"4-15","FirstActionableFrame":"27","BaseDamage":"","Angle":"","BaseKnockBackSetKnockback":"","LandingLag":null,"AutoCancel":null,"KnockbackGrowth":"","MoveType":"ground","IsWeightDependent":false,"Game":"Smash4","Related":{"Smash4":{"Character":"http://api.kuroganehammer.com/api/characters/name/DuckHunt?game=smash4","Self":"http://api.kuroganehammer.com/api/moves/9782dd8ccc7d4d3086fa86c4c8786630?game=smash4"},"Ultimate":{"Character":"http://api.kuroganehammer.com/api/characters/name/DuckHunt?game=ultimate"}},"Links":[{"Rel":"self","Href":"http://api.kuroganehammer.com/api/moves/9782dd8ccc7d4d3086fa86c4c8786630?game=smash4"},{"Rel":"character","Href":"http://api.kuroganehammer.com/api/characters/name/DuckHunt?game=smash4"}]},{"InstanceId":"1b559d36e3d44db99c542dc147ef0d2a","Name":"Back Roll","OwnerId":12,"Owner":"DuckHunt","HitboxActive":"4-15","FirstActionableFrame":"27","BaseDamage":"","Angle":"","BaseKnockBackSetKnockback":"","LandingLag":null,"AutoCancel":null,"KnockbackGrowth":"","MoveType":"ground","IsWeightDependent":false,"Game":"Smash4","Related":{"Smash4":{"Character":"http://api.kuroganehammer.com/api/characters/name/DuckHunt?game=smash4","Self":"http://api.kuroganehammer.com/api/moves/1b559d36e3d44db99c542dc147ef0d2a?game=smash4"},"Ultimate":{"Character":"http://api.kuroganehammer.com/api/characters/name/DuckHunt?game=ultimate"}},"Links":[{"Rel":"self","Href":"http://api.kuroganehammer.com/api/moves/1b559d36e3d44db99c542dc147ef0d2a?game=smash4"},{"Rel":"character","Href":"http://api.kuroganehammer.com/api/characters/name/DuckHunt?game=smash4"}]},{"InstanceId":"152dc6132ad54503928c41755b8bb98e","Name":"Airdodge","OwnerId":12,"Owner":"DuckHunt","HitboxActive":"2-25","FirstActionableFrame":"31","BaseDamage":"","Angle":"","BaseKnockBackSetKnockback":"","LandingLag":null,"AutoCancel":null,"KnockbackGrowth":"","MoveType":"ground","IsWeightDependent":false,"Game":"Smash4","Related":{"Smash4":{"Character":"http://api.kuroganehammer.com/api/characters/name/DuckHunt?game=smash4","Self":"http://api.kuroganehammer.com/api/moves/152dc6132ad54503928c41755b8bb98e?game=smash4"},"Ultimate":{"Character":"http://api.kuroganehammer.com/api/characters/name/DuckHunt?game=ultimate"}},"Links":[{"Rel":"self","Href":"http://api.kuroganehammer.com/api/moves/152dc6132ad54503928c41755b8bb98e?game=smash4"},{"Rel":"character","Href":"http://api.kuroganehammer.com/api/characters/name/DuckHunt?game=smash4"}]},{"InstanceId":"13ae607575bd44ceaa8d262f82fb39ca","Name":"Nair","OwnerId":12,"Owner":"DuckHunt","HitboxActive":"6-8","FirstActionableFrame":"56","BaseDamage":"11","Angle":"361","BaseKnockBackSetKnockback":"30","LandingLag":"17","AutoCancel":"1-3, 44>","KnockbackGrowth":"100","MoveType":"aerial","IsWeightDependent":false,"Game":"Smash4","Related":{"Smash4":{"Character":"http://api.kuroganehammer.com/api/characters/name/DuckHunt?game=smash4","Self":"http://api.kuroganehammer.com/api/moves/13ae607575bd44ceaa8d262f82fb39ca?game=smash4"},"Ultimate":{"Character":"http://api.kuroganehammer.com/api/characters/name/DuckHunt?game=ultimate"}},"Links":[{"Rel":"self","Href":"http://api.kuroganehammer.com/api/moves/13ae607575bd44ceaa8d262f82fb39ca?game=smash4"},{"Rel":"character","Href":"http://api.kuroganehammer.com/api/characters/name/DuckHunt?game=smash4"}]},{"InstanceId":"f5d049a3e10441a0a5197ee4bf9ac487","Name":"Nair (Late)","OwnerId":12,"Owner":"DuckHunt","HitboxActive":"9-37","FirstActionableFrame":"-","BaseDamage":"5","Angle":"361","BaseKnockBackSetKnockback":"22","LandingLag":"-","AutoCancel":"-","KnockbackGrowth":"90","MoveType":"aerial","IsWeightDependent":false,"Game":"Smash4","Related":{"Smash4":{"Character":"http://api.kuroganehammer.com/api/characters/name/DuckHunt?game=smash4","Self":"http://api.kuroganehammer.com/api/moves/f5d049a3e10441a0a5197ee4bf9ac487?game=smash4"},"Ultimate":{"Character":"http://api.kuroganehammer.com/api/characters/name/DuckHunt?game=ultimate"}},"Links":[{"Rel":"self","Href":"http://api.kuroganehammer.com/api/moves/f5d049a3e10441a0a5197ee4bf9ac487?game=smash4"},{"Rel":"character","Href":"http://api.kuroganehammer.com/api/characters/name/DuckHunt?game=smash4"}]},{"InstanceId":"b5bdd5829f4045e68fe380fc5cfc82d8","Name":"Fair (Early)","OwnerId":12,"Owner":"DuckHunt","HitboxActive":"7-8","FirstActionableFrame":"46","BaseDamage":"6.5","Angle":"48","BaseKnockBackSetKnockback":"40","LandingLag":"15","AutoCancel":"1-4, 46>","KnockbackGrowth":"80","MoveType":"aerial","IsWeightDependent":false,"Game":"Smash4","Related":{"Smash4":{"Character":"http://api.kuroganehammer.com/api/characters/name/DuckHunt?game=smash4","Self":"http://api.kuroganehammer.com/api/moves/b5bdd5829f4045e68fe380fc5cfc82d8?game=smash4"},"Ultimate":{"Character":"http://api.kuroganehammer.com/api/characters/name/DuckHunt?game=ultimate"}},"Links":[{"Rel":"self","Href":"http://api.kuroganehammer.com/api/moves/b5bdd5829f4045e68fe380fc5cfc82d8?game=smash4"},{"Rel":"character","Href":"http://api.kuroganehammer.com/api/characters/name/DuckHunt?game=smash4"}]},{"InstanceId":"0308392f3ea542d8a429643196760eeb","Name":"Fair","OwnerId":12,"Owner":"DuckHunt","HitboxActive":"9-10","FirstActionableFrame":"-","BaseDamage":"10/6.5","Angle":"48","BaseKnockBackSetKnockback":"30/40","LandingLag":"-","AutoCancel":"-","KnockbackGrowth":"80","MoveType":"aerial","IsWeightDependent":false,"Game":"Smash4","Related":{"Smash4":{"Character":"http://api.kuroganehammer.com/api/characters/name/DuckHunt?game=smash4","Self":"http://api.kuroganehammer.com/api/moves/0308392f3ea542d8a429643196760eeb?game=smash4"},"Ultimate":{"Character":"http://api.kuroganehammer.com/api/characters/name/DuckHunt?game=ultimate"}},"Links":[{"Rel":"self","Href":"http://api.kuroganehammer.com/api/moves/0308392f3ea542d8a429643196760eeb?game=smash4"},{"Rel":"character","Href":"http://api.kuroganehammer.com/api/characters/name/DuckHunt?game=smash4"}]},{"InstanceId":"8a0c34cf86e94d088b78ba68f351451a","Name":"Fair (Late)","OwnerId":12,"Owner":"DuckHunt","HitboxActive":"11-12","FirstActionableFrame":"-","BaseDamage":"7.5","Angle":"48","BaseKnockBackSetKnockback":"30","LandingLag":"-","AutoCancel":"-","KnockbackGrowth":"80","MoveType":"aerial","IsWeightDependent":false,"Game":"Smash4","Related":{"Smash4":{"Character":"http://api.kuroganehammer.com/api/characters/name/DuckHunt?game=smash4","Self":"http://api.kuroganehammer.com/api/moves/8a0c34cf86e94d088b78ba68f351451a?game=smash4"},"Ultimate":{"Character":"http://api.kuroganehammer.com/api/characters/name/DuckHunt?game=ultimate"}},"Links":[{"Rel":"self","Href":"http://api.kuroganehammer.com/api/moves/8a0c34cf86e94d088b78ba68f351451a?game=smash4"},{"Rel":"character","Href":"http://api.kuroganehammer.com/api/characters/name/DuckHunt?game=smash4"}]},{"InstanceId":"aace614a2ed3498882bd4f8bfef97e2a","Name":"Bair","OwnerId":12,"Owner":"DuckHunt","HitboxActive":"7-8","FirstActionableFrame":"42","BaseDamage":"10/12","Angle":"361","BaseKnockBackSetKnockback":"40/30","LandingLag":"24","AutoCancel":"1-3, 35>","KnockbackGrowth":"90","MoveType":"aerial","IsWeightDependent":false,"Game":"Smash4","Related":{"Smash4":{"Character":"http://api.kuroganehammer.com/api/characters/name/DuckHunt?game=smash4","Self":"http://api.kuroganehammer.com/api/moves/aace614a2ed3498882bd4f8bfef97e2a?game=smash4"},"Ultimate":{"Character":"http://api.kuroganehammer.com/api/characters/name/DuckHunt?game=ultimate"}},"Links":[{"Rel":"self","Href":"http://api.kuroganehammer.com/api/moves/aace614a2ed3498882bd4f8bfef97e2a?game=smash4"},{"Rel":"character","Href":"http://api.kuroganehammer.com/api/characters/name/DuckHunt?game=smash4"}]},{"InstanceId":"01b682b52e0a427c9bbbb5b0f2698532","Name":"Bair (Late)","OwnerId":12,"Owner":"DuckHunt","HitboxActive":"9-10","FirstActionableFrame":"-","BaseDamage":"10.5","Angle":"361","BaseKnockBackSetKnockback":"30","LandingLag":"-","AutoCancel":"-","KnockbackGrowth":"90","MoveType":"aerial","IsWeightDependent":false,"Game":"Smash4","Related":{"Smash4":{"Character":"http://api.kuroganehammer.com/api/characters/name/DuckHunt?game=smash4","Self":"http://api.kuroganehammer.com/api/moves/01b682b52e0a427c9bbbb5b0f2698532?game=smash4"},"Ultimate":{"Character":"http://api.kuroganehammer.com/api/characters/name/DuckHunt?game=ultimate"}},"Links":[{"Rel":"self","Href":"http://api.kuroganehammer.com/api/moves/01b682b52e0a427c9bbbb5b0f2698532?game=smash4"},{"Rel":"character","Href":"http://api.kuroganehammer.com/api/characters/name/DuckHunt?game=smash4"}]},{"InstanceId":"91d6901e9cbf413aa9e158355e97a18b","Name":"Uair (Hits 1-2)","OwnerId":12,"Owner":"DuckHunt","HitboxActive":"6-7, 12-13","FirstActionableFrame":"40","BaseDamage":"3","Angle":"145","BaseKnockBackSetKnockback":"W: 40 B: 9","LandingLag":"18","AutoCancel":"32>","KnockbackGrowth":"100","MoveType":"aerial","IsWeightDependent":false,"Game":"Smash4","Related":{"Smash4":{"Character":"http://api.kuroganehammer.com/api/characters/name/DuckHunt?game=smash4","Self":"http://api.kuroganehammer.com/api/moves/91d6901e9cbf413aa9e158355e97a18b?game=smash4"},"Ultimate":{"Character":"http://api.kuroganehammer.com/api/characters/name/DuckHunt?game=ultimate"}},"Links":[{"Rel":"self","Href":"http://api.kuroganehammer.com/api/moves/91d6901e9cbf413aa9e158355e97a18b?game=smash4"},{"Rel":"character","Href":"http://api.kuroganehammer.com/api/characters/name/DuckHunt?game=smash4"}]},{"InstanceId":"74b8cf2a505340d59610f92908f59e70","Name":"Uair (Hit 3)","OwnerId":12,"Owner":"DuckHunt","HitboxActive":"20-21","FirstActionableFrame":"-","BaseDamage":"6","Angle":"91","BaseKnockBackSetKnockback":"50","LandingLag":"-","AutoCancel":"-","KnockbackGrowth":"120","MoveType":"aerial","IsWeightDependent":false,"Game":"Smash4","Related":{"Smash4":{"Character":"http://api.kuroganehammer.com/api/characters/name/DuckHunt?game=smash4","Self":"http://api.kuroganehammer.com/api/moves/74b8cf2a505340d59610f92908f59e70?game=smash4"},"Ultimate":{"Character":"http://api.kuroganehammer.com/api/characters/name/DuckHunt?game=ultimate"}},"Links":[{"Rel":"self","Href":"http://api.kuroganehammer.com/api/moves/74b8cf2a505340d59610f92908f59e70?game=smash4"},{"Rel":"character","Href":"http://api.kuroganehammer.com/api/characters/name/DuckHunt?game=smash4"}]},{"InstanceId":"c287d6751e7e49eebcf44c390a3e4164","Name":"Dair (Hit 1)","OwnerId":12,"Owner":"DuckHunt","HitboxActive":"14","FirstActionableFrame":"60","BaseDamage":"5","Angle":"130/255","BaseKnockBackSetKnockback":"20","LandingLag":"34","AutoCancel":"1-3, 33>","KnockbackGrowth":"20","MoveType":"aerial","IsWeightDependent":false,"Game":"Smash4","Related":{"Smash4":{"Character":"http://api.kuroganehammer.com/api/characters/name/DuckHunt?game=smash4","Self":"http://api.kuroganehammer.com/api/moves/c287d6751e7e49eebcf44c390a3e4164?game=smash4"},"Ultimate":{"Character":"http://api.kuroganehammer.com/api/characters/name/DuckHunt?game=ultimate"}},"Links":[{"Rel":"self","Href":"http://api.kuroganehammer.com/api/moves/c287d6751e7e49eebcf44c390a3e4164?game=smash4"},{"Rel":"character","Href":"http://api.kuroganehammer.com/api/characters/name/DuckHunt?game=smash4"}]},{"InstanceId":"a4d983f77b584e8fa5e786f045781a9d","Name":"Dair (Hit 2)","OwnerId":12,"Owner":"DuckHunt","HitboxActive":"20","FirstActionableFrame":"-","BaseDamage":"10","Angle":"270/70","BaseKnockBackSetKnockback":"10","LandingLag":"-","AutoCancel":"-","KnockbackGrowth":"80/90","MoveType":"aerial","IsWeightDependent":false,"Game":"Smash4","Related":{"Smash4":{"Character":"http://api.kuroganehammer.com/api/characters/name/DuckHunt?game=smash4","Self":"http://api.kuroganehammer.com/api/moves/a4d983f77b584e8fa5e786f045781a9d?game=smash4"},"Ultimate":{"Character":"http://api.kuroganehammer.com/api/characters/name/DuckHunt?game=ultimate"}},"Links":[{"Rel":"self","Href":"http://api.kuroganehammer.com/api/moves/a4d983f77b584e8fa5e786f045781a9d?game=smash4"},{"Rel":"character","Href":"http://api.kuroganehammer.com/api/characters/name/DuckHunt?game=smash4"}]},{"InstanceId":"1d314346b3a24e829c59ac132542f82e","Name":"Trick Shot","OwnerId":12,"Owner":"DuckHunt","HitboxActive":"16-","FirstActionableFrame":"46","BaseDamage":"2","Angle":"80","BaseKnockBackSetKnockback":"50","LandingLag":null,"AutoCancel":null,"KnockbackGrowth":"40","MoveType":"special","IsWeightDependent":false,"Game":"Smash4","Related":{"Smash4":{"Character":"http://api.kuroganehammer.com/api/characters/name/DuckHunt?game=smash4","Self":"http://api.kuroganehammer.com/api/moves/1d314346b3a24e829c59ac132542f82e?game=smash4"},"Ultimate":{"Character":"http://api.kuroganehammer.com/api/characters/name/DuckHunt?game=ultimate"}},"Links":[{"Rel":"self","Href":"http://api.kuroganehammer.com/api/moves/1d314346b3a24e829c59ac132542f82e?game=smash4"},{"Rel":"character","Href":"http://api.kuroganehammer.com/api/characters/name/DuckHunt?game=smash4"}]},{"InstanceId":"35b474d12c5a4d528dc639f0774efcc0","Name":"Trick Shot (Reticle Hit)","OwnerId":12,"Owner":"DuckHunt","HitboxActive":"1-2","FirstActionableFrame":"-","BaseDamage":"1.8","Angle":"60","BaseKnockBackSetKnockback":"30","LandingLag":null,"AutoCancel":null,"KnockbackGrowth":"100","MoveType":"special","IsWeightDependent":false,"Game":"Smash4","Related":{"Smash4":{"Character":"http://api.kuroganehammer.com/api/characters/name/DuckHunt?game=smash4","Self":"http://api.kuroganehammer.com/api/moves/35b474d12c5a4d528dc639f0774efcc0?game=smash4"},"Ultimate":{"Character":"http://api.kuroganehammer.com/api/characters/name/DuckHunt?game=ultimate"}},"Links":[{"Rel":"self","Href":"http://api.kuroganehammer.com/api/moves/35b474d12c5a4d528dc639f0774efcc0?game=smash4"},{"Rel":"character","Href":"http://api.kuroganehammer.com/api/characters/name/DuckHunt?game=smash4"}]},{"InstanceId":"6ab8e0242cf649018eb6c3ad5864b028","Name":"Trick Shot (Explosion)","OwnerId":12,"Owner":"DuckHunt","HitboxActive":"1-2","FirstActionableFrame":"-","BaseDamage":"8","Angle":"80","BaseKnockBackSetKnockback":"40","LandingLag":null,"AutoCancel":null,"KnockbackGrowth":"110","MoveType":"special","IsWeightDependent":false,"Game":"Smash4","Related":{"Smash4":{"Character":"http://api.kuroganehammer.com/api/characters/name/DuckHunt?game=smash4","Self":"http://api.kuroganehammer.com/api/moves/6ab8e0242cf649018eb6c3ad5864b028?game=smash4"},"Ultimate":{"Character":"http://api.kuroganehammer.com/api/characters/name/DuckHunt?game=ultimate"}},"Links":[{"Rel":"self","Href":"http://api.kuroganehammer.com/api/moves/6ab8e0242cf649018eb6c3ad5864b028?game=smash4"},{"Rel":"character","Href":"http://api.kuroganehammer.com/api/characters/name/DuckHunt?game=smash4"}]},{"InstanceId":"d02685a212d049dfa887448e7dfff41d","Name":"Clay Shooting (Pidgeon)","OwnerId":12,"Owner":"DuckHunt","HitboxActive":"17-","FirstActionableFrame":"66","BaseDamage":"2","Angle":"75","BaseKnockBackSetKnockback":"40","LandingLag":null,"AutoCancel":null,"KnockbackGrowth":"70","MoveType":"special","IsWeightDependent":false,"Game":"Smash4","Related":{"Smash4":{"Character":"http://api.kuroganehammer.com/api/characters/name/DuckHunt?game=smash4","Self":"http://api.kuroganehammer.com/api/moves/d02685a212d049dfa887448e7dfff41d?game=smash4"},"Ultimate":{"Character":"http://api.kuroganehammer.com/api/characters/name/DuckHunt?game=ultimate"}},"Links":[{"Rel":"self","Href":"http://api.kuroganehammer.com/api/moves/d02685a212d049dfa887448e7dfff41d?game=smash4"},{"Rel":"character","Href":"http://api.kuroganehammer.com/api/characters/name/DuckHunt?game=smash4"}]},{"InstanceId":"dc70c6dcba7c4e13982e9937b322be0a","Name":"Clay Shooting (Reticle Hits 1-3)","OwnerId":12,"Owner":"DuckHunt","HitboxActive":"6, 14, 17","FirstActionableFrame":"-","BaseDamage":"1.8","Angle":"60","BaseKnockBackSetKnockback":"10","LandingLag":null,"AutoCancel":null,"KnockbackGrowth":"10","MoveType":"special","IsWeightDependent":false,"Game":"Smash4","Related":{"Smash4":{"Character":"http://api.kuroganehammer.com/api/characters/name/DuckHunt?game=smash4","Self":"http://api.kuroganehammer.com/api/moves/dc70c6dcba7c4e13982e9937b322be0a?game=smash4"},"Ultimate":{"Character":"http://api.kuroganehammer.com/api/characters/name/DuckHunt?game=ultimate"}},"Links":[{"Rel":"self","Href":"http://api.kuroganehammer.com/api/moves/dc70c6dcba7c4e13982e9937b322be0a?game=smash4"},{"Rel":"character","Href":"http://api.kuroganehammer.com/api/characters/name/DuckHunt?game=smash4"}]},{"InstanceId":"45dc7b6927d0485ba4a232043718bcab","Name":"Clay Shooting (Reticle Hit 4)","OwnerId":12,"Owner":"DuckHunt","HitboxActive":"18","FirstActionableFrame":"-","BaseDamage":"5","Angle":"60","BaseKnockBackSetKnockback":"30","LandingLag":null,"AutoCancel":null,"KnockbackGrowth":"100","MoveType":"special","IsWeightDependent":false,"Game":"Smash4","Related":{"Smash4":{"Character":"http://api.kuroganehammer.com/api/characters/name/DuckHunt?game=smash4","Self":"http://api.kuroganehammer.com/api/moves/45dc7b6927d0485ba4a232043718bcab?game=smash4"},"Ultimate":{"Character":"http://api.kuroganehammer.com/api/characters/name/DuckHunt?game=ultimate"}},"Links":[{"Rel":"self","Href":"http://api.kuroganehammer.com/api/moves/45dc7b6927d0485ba4a232043718bcab?game=smash4"},{"Rel":"character","Href":"http://api.kuroganehammer.com/api/characters/name/DuckHunt?game=smash4"}]},{"InstanceId":"7cb1e72422b0419e823742f65a75203d","Name":"Duck Jump","OwnerId":12,"Owner":"DuckHunt","HitboxActive":"-","FirstActionableFrame":"-","BaseDamage":"-","Angle":"-","BaseKnockBackSetKnockback":"-","LandingLag":null,"AutoCancel":null,"KnockbackGrowth":"-","MoveType":"special","IsWeightDependent":false,"Game":"Smash4","Related":{"Smash4":{"Character":"http://api.kuroganehammer.com/api/characters/name/DuckHunt?game=smash4","Self":"http://api.kuroganehammer.com/api/moves/7cb1e72422b0419e823742f65a75203d?game=smash4"},"Ultimate":{"Character":"http://api.kuroganehammer.com/api/characters/name/DuckHunt?game=ultimate"}},"Links":[{"Rel":"self","Href":"http://api.kuroganehammer.com/api/moves/7cb1e72422b0419e823742f65a75203d?game=smash4"},{"Rel":"character","Href":"http://api.kuroganehammer.com/api/characters/name/DuckHunt?game=smash4"}]},{"InstanceId":"7621b6e73b324be8af7dbea027c5e1eb","Name":"Wild Gunman","OwnerId":12,"Owner":"DuckHunt","HitboxActive":"Gunman Generated: 6, 5% HP","FirstActionableFrame":"45","BaseDamage":"-","Angle":"-","BaseKnockBackSetKnockback":"-","LandingLag":null,"AutoCancel":null,"KnockbackGrowth":"-","MoveType":"special","IsWeightDependent":false,"Game":"Smash4","Related":{"Smash4":{"Character":"http://api.kuroganehammer.com/api/characters/name/DuckHunt?game=smash4","Self":"http://api.kuroganehammer.com/api/moves/7621b6e73b324be8af7dbea027c5e1eb?game=smash4"},"Ultimate":{"Character":"http://api.kuroganehammer.com/api/characters/name/DuckHunt?game=ultimate"}},"Links":[{"Rel":"self","Href":"http://api.kuroganehammer.com/api/moves/7621b6e73b324be8af7dbea027c5e1eb?game=smash4"},{"Rel":"character","Href":"http://api.kuroganehammer.com/api/characters/name/DuckHunt?game=smash4"}]},{"InstanceId":"b1cb590eb9cb4b169fea8ef1ce0f383f","Name":"Wild Gunman (Sombrero)","OwnerId":12,"Owner":"DuckHunt","HitboxActive":"71","FirstActionableFrame":"-","BaseDamage":"7","Angle":"70","BaseKnockBackSetKnockback":"30","LandingLag":null,"AutoCancel":null,"KnockbackGrowth":"105","MoveType":"special","IsWeightDependent":false,"Game":"Smash4","Related":{"Smash4":{"Character":"http://api.kuroganehammer.com/api/characters/name/DuckHunt?game=smash4","Self":"http://api.kuroganehammer.com/api/moves/b1cb590eb9cb4b169fea8ef1ce0f383f?game=smash4"},"Ultimate":{"Character":"http://api.kuroganehammer.com/api/characters/name/DuckHunt?game=ultimate"}},"Links":[{"Rel":"self","Href":"http://api.kuroganehammer.com/api/moves/b1cb590eb9cb4b169fea8ef1ce0f383f?game=smash4"},{"Rel":"character","Href":"http://api.kuroganehammer.com/api/characters/name/DuckHunt?game=smash4"}]},{"InstanceId":"be6e8a71d6c9432fb7b5583f6abe9733","Name":"Wild Gunman (Brown Coat & Hat)","OwnerId":12,"Owner":"DuckHunt","HitboxActive":"53","FirstActionableFrame":"-","BaseDamage":"6","Angle":"65","BaseKnockBackSetKnockback":"30","LandingLag":null,"AutoCancel":null,"KnockbackGrowth":"105","MoveType":"special","IsWeightDependent":false,"Game":"Smash4","Related":{"Smash4":{"Character":"http://api.kuroganehammer.com/api/characters/name/DuckHunt?game=smash4","Self":"http://api.kuroganehammer.com/api/moves/be6e8a71d6c9432fb7b5583f6abe9733?game=smash4"},"Ultimate":{"Character":"http://api.kuroganehammer.com/api/characters/name/DuckHunt?game=ultimate"}},"Links":[{"Rel":"self","Href":"http://api.kuroganehammer.com/api/moves/be6e8a71d6c9432fb7b5583f6abe9733?game=smash4"},{"Rel":"character","Href":"http://api.kuroganehammer.com/api/characters/name/DuckHunt?game=smash4"}]},{"InstanceId":"29096c8ed13b47adaea2396fa11096ee","Name":"Wild Gunman (Black Coat & Hat)","OwnerId":12,"Owner":"DuckHunt","HitboxActive":"65","FirstActionableFrame":"-","BaseDamage":"5","Angle":"50","BaseKnockBackSetKnockback":"30","LandingLag":null,"AutoCancel":null,"KnockbackGrowth":"105","MoveType":"special","IsWeightDependent":false,"Game":"Smash4","Related":{"Smash4":{"Character":"http://api.kuroganehammer.com/api/characters/name/DuckHunt?game=smash4","Self":"http://api.kuroganehammer.com/api/moves/29096c8ed13b47adaea2396fa11096ee?game=smash4"},"Ultimate":{"Character":"http://api.kuroganehammer.com/api/characters/name/DuckHunt?game=ultimate"}},"Links":[{"Rel":"self","Href":"http://api.kuroganehammer.com/api/moves/29096c8ed13b47adaea2396fa11096ee?game=smash4"},{"Rel":"character","Href":"http://api.kuroganehammer.com/api/characters/name/DuckHunt?game=smash4"}]},{"InstanceId":"ad554085407845eb8d2848d37dd2a43e","Name":"Wild Gunman (White Shirt & Brown Hat)","OwnerId":12,"Owner":"DuckHunt","HitboxActive":"89","FirstActionableFrame":"-","BaseDamage":"4","Angle":"65","BaseKnockBackSetKnockback":"30","LandingLag":null,"AutoCancel":null,"KnockbackGrowth":"112","MoveType":"special","IsWeightDependent":false,"Game":"Smash4","Related":{"Smash4":{"Character":"http://api.kuroganehammer.com/api/characters/name/DuckHunt?game=smash4","Self":"http://api.kuroganehammer.com/api/moves/ad554085407845eb8d2848d37dd2a43e?game=smash4"},"Ultimate":{"Character":"http://api.kuroganehammer.com/api/characters/name/DuckHunt?game=ultimate"}},"Links":[{"Rel":"self","Href":"http://api.kuroganehammer.com/api/moves/ad554085407845eb8d2848d37dd2a43e?game=smash4"},{"Rel":"character","Href":"http://api.kuroganehammer.com/api/characters/name/DuckHunt?game=smash4"}]},{"InstanceId":"506e78d4d14d4a80964eaee1867a5100","Name":"Wild Gunman (Black Vest & Brown Hat)","OwnerId":12,"Owner":"DuckHunt","HitboxActive":"77","FirstActionableFrame":"-","BaseDamage":"4","Angle":"50","BaseKnockBackSetKnockback":"30","LandingLag":null,"AutoCancel":null,"KnockbackGrowth":"105","MoveType":"special","IsWeightDependent":false,"Game":"Smash4","Related":{"Smash4":{"Character":"http://api.kuroganehammer.com/api/characters/name/DuckHunt?game=smash4","Self":"http://api.kuroganehammer.com/api/moves/506e78d4d14d4a80964eaee1867a5100?game=smash4"},"Ultimate":{"Character":"http://api.kuroganehammer.com/api/characters/name/DuckHunt?game=ultimate"}},"Links":[{"Rel":"self","Href":"http://api.kuroganehammer.com/api/moves/506e78d4d14d4a80964eaee1867a5100?game=smash4"},{"Rel":"character","Href":"http://api.kuroganehammer.com/api/characters/name/DuckHunt?game=smash4"}]},{"InstanceId":"eb65d3980a604cb3bb041b1302cde166","Name":"Fthrow","OwnerId":12,"Owner":"DuckHunt","HitboxActive":null,"FirstActionableFrame":null,"BaseDamage":"8","Angle":"45","BaseKnockBackSetKnockback":"60","LandingLag":null,"AutoCancel":null,"KnockbackGrowth":"65","MoveType":"throw","IsWeightDependent":true,"Game":"Smash4","Related":{"Smash4":{"Character":"http://api.kuroganehammer.com/api/characters/name/DuckHunt?game=smash4","Self":"http://api.kuroganehammer.com/api/moves/eb65d3980a604cb3bb041b1302cde166?game=smash4"},"Ultimate":{"Character":"http://api.kuroganehammer.com/api/characters/name/DuckHunt?game=ultimate"}},"Links":[{"Rel":"self","Href":"http://api.kuroganehammer.com/api/moves/eb65d3980a604cb3bb041b1302cde166?game=smash4"},{"Rel":"character","Href":"http://api.kuroganehammer.com/api/characters/name/DuckHunt?game=smash4"}]},{"InstanceId":"d087d3fd8dae4f959f4c1451c0cadd7b","Name":"Bthrow","OwnerId":12,"Owner":"DuckHunt","HitboxActive":null,"FirstActionableFrame":null,"BaseDamage":"9","Angle":"45","BaseKnockBackSetKnockback":"62","LandingLag":null,"AutoCancel":null,"KnockbackGrowth":"50","MoveType":"throw","IsWeightDependent":true,"Game":"Smash4","Related":{"Smash4":{"Character":"http://api.kuroganehammer.com/api/characters/name/DuckHunt?game=smash4","Self":"http://api.kuroganehammer.com/api/moves/d087d3fd8dae4f959f4c1451c0cadd7b?game=smash4"},"Ultimate":{"Character":"http://api.kuroganehammer.com/api/characters/name/DuckHunt?game=ultimate"}},"Links":[{"Rel":"self","Href":"http://api.kuroganehammer.com/api/moves/d087d3fd8dae4f959f4c1451c0cadd7b?game=smash4"},{"Rel":"character","Href":"http://api.kuroganehammer.com/api/characters/name/DuckHunt?game=smash4"}]},{"InstanceId":"5c68adbd171d42978ababccdf0e2642a","Name":"Uthrow","OwnerId":12,"Owner":"DuckHunt","HitboxActive":null,"FirstActionableFrame":null,"BaseDamage":"6","Angle":"88","BaseKnockBackSetKnockback":"70","LandingLag":null,"AutoCancel":null,"KnockbackGrowth":"80","MoveType":"throw","IsWeightDependent":true,"Game":"Smash4","Related":{"Smash4":{"Character":"http://api.kuroganehammer.com/api/characters/name/DuckHunt?game=smash4","Self":"http://api.kuroganehammer.com/api/moves/5c68adbd171d42978ababccdf0e2642a?game=smash4"},"Ultimate":{"Character":"http://api.kuroganehammer.com/api/characters/name/DuckHunt?game=ultimate"}},"Links":[{"Rel":"self","Href":"http://api.kuroganehammer.com/api/moves/5c68adbd171d42978ababccdf0e2642a?game=smash4"},{"Rel":"character","Href":"http://api.kuroganehammer.com/api/characters/name/DuckHunt?game=smash4"}]},{"InstanceId":"8791e394079a4243b5d2185fa3ce5bce","Name":"Dthrow","OwnerId":12,"Owner":"DuckHunt","HitboxActive":null,"FirstActionableFrame":null,"BaseDamage":"5","Angle":"80","BaseKnockBackSetKnockback":"70","LandingLag":null,"AutoCancel":null,"KnockbackGrowth":"50","MoveType":"throw","IsWeightDependent":true,"Game":"Smash4","Related":{"Smash4":{"Character":"http://api.kuroganehammer.com/api/characters/name/DuckHunt?game=smash4","Self":"http://api.kuroganehammer.com/api/moves/8791e394079a4243b5d2185fa3ce5bce?game=smash4"},"Ultimate":{"Character":"http://api.kuroganehammer.com/api/characters/name/DuckHunt?game=ultimate"}},"Links":[{"Rel":"self","Href":"http://api.kuroganehammer.com/api/moves/8791e394079a4243b5d2185fa3ce5bce?game=smash4"},{"Rel":"character","Href":"http://api.kuroganehammer.com/api/characters/name/DuckHunt?game=smash4"}]}]